[
  {
    "id": "dffd2108-cded-4eb2-b0f0-01cb878314d4",
    "document_name": "Technical Feasibility Strategy",
    "description": "Strategy for demonstrating technical feasibility of platform-neutral and fallback-capable authentication.",
    "responsible_role_type": "Lead Researcher",
    "document_template_primary": null,
    "document_template_secondary": null,
    "steps_to_create": [
      "Define specific technical requirements",
      "Develop demonstrators"
    ],
    "approval_authorities": "Project Manager"
  },
  {
    "id": "05ef9eb9-4789-4d4e-9ac3-3402046b99e4",
    "document_name": "Policy Advocacy Strategy",
    "description": "Strategy for influencing policy and advocacy efforts towards platform neutrality.",
    "responsible_role_type": "Policy & Public Affairs Coordinator",
    "document_template_primary": null,
    "document_template_secondary": null,
    "steps_to_create": [
      "Define messaging",
      "Identify key stakeholders"
    ],
    "approval_authorities": "Project Manager"
  },
  {
    "id": "ad02b681-a749-4538-bb33-25dc580606c9",
    "document_name": "Coalition Building Strategy",
    "description": "Strategy for building a coalition of support for platform-neutral authentication.",
    "responsible_role_type": "Policy & Public Affairs Coordinator",
    "document_template_primary": null,
    "document_template_secondary": null,
    "steps_to_create": [
      "Identify potential stakeholders",
      "Develop communication plan"
    ],
    "approval_authorities": "Project Manager"
  },
  {
    "id": "da96f917-c2e5-494c-8b73-1708e59447cf",
    "document_name": "Procurement Influence Strategy",
    "description": "Strategy for influencing procurement decisions towards platform neutrality.",
    "responsible_role_type": "Policy & Public Affairs Coordinator",
    "document_template_primary": null,
    "document_template_secondary": null,
    "steps_to_create": [
      "Define procurement language",
      "Identify key stakeholders"
    ],
    "approval_authorities": "Project Manager"
  },
  {
    "id": "0db3f50a-b739-4860-a666-b43ed1bd6022",
    "document_name": "EU Standards Engagement Strategy",
    "description": "Strategy for influencing EU standards towards platform neutrality.",
    "responsible_role_type": "Policy & Public Affairs Coordinator",
    "document_template_primary": null,
    "document_template_secondary": null,
    "steps_to_create": [
      "Identify relevant standards bodies",
      "Develop engagement plan"
    ],
    "approval_authorities": "Project Manager"
  },
  {
    "id": "512c00d7-de98-494d-ba5c-8c34b3c873ff",
    "document_name": "Risk Management Plan",
    "description": "Plan for managing risks associated with the project.",
    "responsible_role_type": "Risk Management Consultant",
    "document_template_primary": null,
    "document_template_secondary": null,
    "steps_to_create": [
      "Conduct risk assessment",
      "Develop mitigation plans"
    ],
    "approval_authorities": "Project Manager"
  },
  {
    "id": "1c9c5cdf-042d-43d8-9d66-71b1e7c332f9",
    "document_name": "Baseline Assessment of Fertility Trends",
    "description": "Report assessing current fertility trends in Denmark.",
    "responsible_role_type": "Lead Researcher",
    "document_template_primary": null,
    "document_template_secondary": null,
    "steps_to_create": [
      "Conduct literature review",
      "Analyze data"
    ],
    "approval_authorities": "Project Manager"
  },
  {
    "id": "4d0a5efa-fead-498c-b601-61961d26b928",
    "document_name": "Risk Register",
    "description": "Document outlining identified risks and mitigation strategies.",
    "responsible_role_type": "Risk Management Consultant",
    "document_template_primary": null,
    "document_template_secondary": null,
    "steps_to_create": [
      "Conduct risk assessment",
      "Develop mitigation plans"
    ],
    "approval_authorities": "Project Manager"
  },
  {
    "id": "4acf85c5-78bd-47c8-a10a-7a9fdef52bb9",
    "document_name": "Communication Plan",
    "description": "Plan for communicating project updates and progress.",
    "responsible_role_type": "Policy & Public Affairs Coordinator",
    "document_template_primary": null,
    "document_template_secondary": null,
    "steps_to_create": [
      "Identify target audiences",
      "Develop messaging"
    ],
    "approval_authorities": "Project Manager"
  }
]